wiring_rs-0.1.1.dist-info/METADATA
wiring_rs-0.1.1.dist-info/WHEEL
wiring_rs/__init__.py
wiring_rs/wiring_rs.abi3.so
wiring_rs-0.1.1.dist-info/RECORD
