Metadata-Version: 2.1
Name: wiring_rs
Version: 0.1.1
Author: chris <chris.kind.man@gmail.com>
Author-email: chris <chris.kind.man@gmail.com>
